range_coder-1.1.dist-info/WHEEL
range_coder-1.1.dist-info/top_level.txt
range_coder-1.1.dist-info/METADATA
range_coder-1.1.dist-info/RECORD
range_coder/__init__.py
range_coder/_range_coder.cpython-34m.so
