Metadata-Version: 2.1
Name: range-coder
Version: 1.1
Summary: A fast implementation of a range coder
Home-page: UNKNOWN
Author: UNKNOWN
Author-email: UNKNOWN
License: BSD
Platform: UNKNOWN
